saitama/__init__.py
saitama/__main__.py
saitama/__version__.py
saitama/lib/__init__.py
saitama/lib/conf.py
saitama/lib/parser.py
saitama/py.typed
saitama/queries/__init__.py
saitama/queries/migration.py
saitama/queries/test.py
saitama/subcommands/__init__.py
saitama/subcommands/common.py
saitama/subcommands/migrate.py
saitama/subcommands/test.py
saitama-0.6.0.dist-info/LICENSE.md
saitama-0.6.0.dist-info/METADATA
saitama-0.6.0.dist-info/WHEEL
saitama-0.6.0.dist-info/entry_points.txt
saitama-0.6.0.dist-info/RECORD
