Metadata-Version: 2.3
Name: saitama
Version: 0.6.0
Summary: A python toolset to manage postgres migrations and testing
Home-page: https://saitama.readthedocs.io/en/stable/
License: BSD-3-Clause
Keywords: postgres,testing
Author: Stephanos Kuma
Author-email: "Stephanos Kuma" <stephanos@kuma.ai>
Requires-Python: >=3.9
Classifier: Development Status :: 3 - Alpha
Classifier: Intended Audience :: Developers
Classifier: License :: OSI Approved :: BSD License
Classifier: Operating System :: OS Independent
Classifier: Programming Language :: Python :: 3 :: Only
Classifier: Topic :: Database
Requires-Dist: dj-settings (~=6.0)
Requires-Dist: psycopg (~=3.0)
Requires-Dist: pyutilkit (~=0.10)
Project-URL: Documentation, https://saitama.readthedocs.io/en/stable/
Project-URL: Repository, https://github.com/spapanik/saitama
